pynetlogo/__init__.py
pynetlogo/core.py
pynetlogo/java/netlogolink.jar
pynetlogo/java/readme.md
pynetlogo/java/netLogoLink/NLResult.java
pynetlogo/java/netLogoLink/NetLogoLink.java
pynetlogo-0.5.2.dist-info/LICENSE.md
pynetlogo-0.5.2.dist-info/METADATA
pynetlogo-0.5.2.dist-info/WHEEL
pynetlogo-0.5.2.dist-info/top_level.txt
pynetlogo-0.5.2.dist-info/RECORD
