Metadata-Version: 2.1
Name: pynetlogo
Version: 0.5.2
Summary: python link for dynamic interaction with NetLogo
Author-email: Jan Kwakkel <j.h.kwakkel@tudelft.nl>
License: Copyright (c) 2010-2018, Delft University of Technology All rights reserved.
Project-URL: Homepage, https://github.com/quaquel/pyNetLogo
Project-URL: Documentation, https://pynetlogo.readthedocs.io
Project-URL: Bug Tracker, https://github.com/quaquel/pynetlogo/issues
Classifier: Programming Language :: Python :: 3
Classifier: License :: OSI Approved :: BSD License
Classifier: Operating System :: OS Independent
Requires-Python: >=3.8
License-File: LICENSE.md
Requires-Dist: pandas
Requires-Dist: numpy
Requires-Dist: jpype1
Provides-Extra: docs
Requires-Dist: sphinx; extra == "docs"
Requires-Dist: nbsphinx; extra == "docs"
Requires-Dist: myst; extra == "docs"
Requires-Dist: pyscaffold; extra == "docs"
Requires-Dist: myst-parser; extra == "docs"
